[{"id":1548,"symbol":"ABT","name":"Arcblock","circulatingSupply":185999998.36,"totalSupply":186000000,"rank":3004,"type":"crypto"},{"id":198,"symbol":"ACT","name":"Achain","circulatingSupply":750597392,"totalSupply":1000000000,"rank":309,"type":"crypto"},{"id":4924,"symbol":"ACTN","name":"Action Coin","circulatingSupply":1800000000,"totalSupply":2000000000,"rank":753,"type":"crypto"},{"id":9,"symbol":"ADA","name":"Cardano","circulatingSupply":31112484745,"totalSupply":31112484745,"rank":6,"type":"crypto"},{"id":null,"symbol":"ADD","name":"ADD Token","circulatingSupply":null,"totalSupply":null,"rank":2000,"type":"crypto"},{"id":282,"symbol":"ADX","name":"AdEx","circulatingSupply":null,"totalSupply":100000000,"rank":182,"type":"crypto"},{"id":33,"symbol":"AE","name":"Aeternity","circulatingSupply":273652026.1244168,"totalSupply":273685830.16432995,"rank":216,"type":"crypto"},{"id":376,"symbol":"AEON","name":"Aeon","circulatingSupply":15831459,"totalSupply":18400000,"rank":553,"type":"crypto"},{"id":10764,"symbol":"AEUR","name":"Augmint Euro Token","circulatingSupply":null,"totalSupply":null,"rank":10162,"type":"crypto"},{"id":181,"symbol":"AGI","name":"SingularityNET","circulatingSupply":539673260,"totalSupply":1000000000,"rank":178,"type":"crypto"},{"id":4906,"symbol":"AGRS","name":"Agoras Tauchain","circulatingSupply":41987989,"totalSupply":42000000,"rank":2994,"type":"crypto"},{"id":66,"symbol":"AION","name":"Aion","circulatingSupply":9395079.018050283,"totalSupply":465934586.66,"rank":372,"type":"crypto"},{"id":14585,"symbol":"ALGO","name":"Algorand","circulatingSupply":2793189724.6751957,"totalSupply":10000000000,"rank":31,"type":"crypto"},{"id":172,"symbol":"AMB","name":"Ambrosus","circulatingSupply":144590974.53570145,"totalSupply":361477437.53570145,"rank":336,"type":"crypto"},{"id":477,"symbol":"AMP","name":"HyperSpace (Synereo)","circulatingSupply":100728564,"totalSupply":622410799,"rank":375,"type":"crypto"},{"id":37496,"symbol":"AMPL","name":"Ampleforth","circulatingSupply":271714955.57746977,"totalSupply":341285375.34755707,"rank":2933,"type":"crypto"},{"id":182,"symbol":"ANT","name":"Aragon","circulatingSupply":29102722.809523806,"totalSupply":39609523.809523806,"rank":111,"type":"crypto"},{"id":320,"symbol":"APPC","name":"AppCoins","circulatingSupply":100054312,"totalSupply":246203093,"rank":323,"type":"crypto"},{"id":56,"symbol":"ARDR","name":"Ardor","circulatingSupply":998999495,"totalSupply":1000000000,"rank":141,"type":"crypto"},{"id":951,"symbol":"ARG","name":"Argentum","circulatingSupply":10544470,"totalSupply":64000000,"rank":1159,"type":"crypto"},{"id":82,"symbol":"ARK","name":"Ark","circulatingSupply":106408238,"totalSupply":125000000,"rank":172,"type":"crypto"},{"id":289,"symbol":"ARN","name":"Aeron","circulatingSupply":13000000,"totalSupply":20000000,"rank":576,"type":"crypto"},{"id":null,"symbol":"ARNX","name":"Aeron","circulatingSupply":null,"totalSupply":null,"rank":2000,"type":"crypto"},{"id":782,"symbol":"ARY","name":"Block Array","circulatingSupply":68430737.93060976,"totalSupply":88409932.93060976,"rank":1083,"type":"crypto"},{"id":270,"symbol":"AST","name":"AirSwap","circulatingSupply":150000000,"totalSupply":500000000,"rank":228,"type":"crypto"},{"id":786,"symbol":"ATM","name":"ATMChain","circulatingSupply":9999999800,"totalSupply":10000000000,"rank":3701,"type":"crypto"},{"id":1297,"symbol":"ATOM","name":"Cosmos","circulatingSupply":1000000,"totalSupply":1000000,"rank":2673,"type":"crypto"},{"id":null,"symbol":"AUDR","name":"AUDRamp","circulatingSupply":null,"totalSupply":null,"rank":2000,"type":"crypto"},{"id":211,"symbol":"AUTO","name":"Cube","circulatingSupply":6774940000,"totalSupply":7200000000,"rank":588,"type":"crypto"},{"id":null,"symbol":"AYWA","name":"Aywa","circulatingSupply":null,"totalSupply":null,"rank":2000,"type":"crypto"},{"id":11282,"symbol":"BAB","name":"Bitcoin Cash ABC","circulatingSupply":null,"totalSupply":null,"rank":9729,"type":"crypto"},{"id":null,"symbol":"BAL","name":"Balancer","circulatingSupply":null,"totalSupply":null,"rank":2000,"type":"crypto"},{"id":63138,"symbol":"BAND","name":"Band Protocol","circulatingSupply":37612715.5,"totalSupply":100000000,"rank":76,"type":"crypto"},{"id":46,"symbol":"BAT","name":"Basic Attention Token","circulatingSupply":1480319799.9390018,"totalSupply":1500000000,"rank":70,"type":"crypto"},{"id":216,"symbol":"BAY","name":"BitBay","circulatingSupply":null,"totalSupply":null,"rank":2316,"type":"crypto"},{"id":31000,"symbol":"BCBC","name":"BCBC","circulatingSupply":null,"totalSupply":null,"rank":7187,"type":"crypto"},{"id":2962,"symbol":"BCC","name":"BCC","circulatingSupply":20148800.99520422,"totalSupply":20999999.99392029,"rank":7222,"type":"crypto"},{"id":36,"symbol":"BCD","name":"Bitcoin Diamond","circulatingSupply":153756875,"totalSupply":156756875,"rank":123,"type":"crypto"},{"id":4,"symbol":"BCH","name":"Bitcoin Cash","circulatingSupply":18630174.89678966,"totalSupply":18630174.89678966,"rank":9,"type":"crypto"},{"id":4989,"symbol":"BCIO","name":"Blockchain.io","circulatingSupply":46713323.56999997,"totalSupply":46713323.56999997,"rank":6511,"type":"crypto"},{"id":31,"symbol":"BCN","name":"Bytecoin","circulatingSupply":184066827285,"totalSupply":184066827285,"rank":467,"type":"crypto"},{"id":127,"symbol":"BCO","name":"BananaCoin","circulatingSupply":null,"totalSupply":null,"rank":2695,"type":"crypto"},{"id":366,"symbol":"BCPT","name":"BlockMason Credit Protocol","circulatingSupply":90985609,"totalSupply":116158667,"rank":345,"type":"crypto"},{"id":1198,"symbol":"BDL","name":"Bitdeal","circulatingSupply":175583793,"totalSupply":219596262,"rank":2749,"type":"crypto"},{"id":10179,"symbol":"BEAM","name":"Beam","circulatingSupply":73740120,"totalSupply":262800000,"rank":213,"type":"crypto"},{"id":879,"symbol":"BELA","name":"Belacoin","circulatingSupply":38601121,"totalSupply":43770506,"rank":880,"type":"crypto"},{"id":124,"symbol":"BIX","name":"Bibox Token","circulatingSupply":102384714,"totalSupply":265986997,"rank":291,"type":"crypto"},{"id":null,"symbol":"BLCN","name":"BLCN","circulatingSupply":null,"totalSupply":null,"rank":2000,"type":"crypto"},{"id":450,"symbol":"BLK","name":"BlackCoin","circulatingSupply":null,"totalSupply":null,"rank":420,"type":"crypto"},{"id":191,"symbol":"BLOCK","name":"Blocknet","circulatingSupply":null,"totalSupply":null,"rank":2381,"type":"crypto"},{"id":1150,"symbol":"BLZ","name":"Blazecoin","circulatingSupply":256401415.07717362,"totalSupply":500000000,"rank":206,"type":"crypto"},{"id":14,"symbol":"BNB","name":"Binance Coin","circulatingSupply":125692073.45428884,"totalSupply":140345602,"rank":12,"type":"crypto"},{"id":76,"symbol":"BNT","name":"Bancor Network Token","circulatingSupply":101225930.82684268,"totalSupply":101225931.12150662,"rank":98,"type":"crypto"},{"id":712,"symbol":"BNTY","name":"Bounty0x","circulatingSupply":186296643.96,"totalSupply":499999999.96,"rank":776,"type":"crypto"},{"id":null,"symbol":"BOOTY","name":"Booty","circulatingSupply":null,"totalSupply":null,"rank":2000,"type":"crypto"},{"id":161,"symbol":"BOS","name":"BOScoin","circulatingSupply":456838751,"totalSupply":500000000,"rank":710,"type":"crypto"},{"id":439,"symbol":"BPT","name":"Blockport","circulatingSupply":52870932.62921125,"totalSupply":69434799.62921125,"rank":679,"type":"crypto"},{"id":589,"symbol":"BQ","name":"bitqy","circulatingSupply":3112670515,"totalSupply":10000000000,"rank":1684,"type":"crypto"},{"id":140,"symbol":"BRD","name":"Bread","circulatingSupply":88733978,"totalSupply":88862718,"rank":282,"type":"crypto"},{"id":568,"symbol":"BSD","name":"BitSend","circulatingSupply":21185775,"totalSupply":139000000,"rank":890,"type":"crypto"},{"id":4875,"symbol":"BSV","name":"BitcoinSV","circulatingSupply":18628045.39423905,"totalSupply":18628045.39423905,"rank":16,"type":"crypto"},{"id":1,"symbol":"BTC","name":"Bitcoin","circulatingSupply":18603550,"totalSupply":18603550,"rank":1,"type":"crypto"},{"id":3065,"symbol":"BTCD","name":"BitcoinDark","circulatingSupply":1288862,"totalSupply":22000000,"rank":2157,"type":"crypto"},{"id":1967,"symbol":"BTCH","name":"Bitcoin Hush","circulatingSupply":null,"totalSupply":null,"rank":7958,"type":"crypto"},{"id":103,"symbol":"BTCP","name":"Bitcoin Private","circulatingSupply":20524490,"totalSupply":21000000,"rank":522,"type":"crypto"},{"id":721,"symbol":"BTCZ","name":"BitcoinZ","circulatingSupply":null,"totalSupply":null,"rank":1560,"type":"crypto"},{"id":23,"symbol":"BTG","name":"Bitcoin Gold","circulatingSupply":17359099,"totalSupply":17458599,"rank":92,"type":"crypto"},{"id":45,"symbol":"BTM","name":"Bytom","circulatingSupply":1649230725,"totalSupply":2100000000,"rank":122,"type":"crypto"},{"id":32,"symbol":"BTS","name":"BitShares","circulatingSupply":2710195991,"totalSupply":3600570502,"rank":155,"type":"crypto"},{"id":4392,"symbol":"BTT","name":"BitTorrent","circulatingSupply":null,"totalSupply":null,"rank":6754,"type":"crypto"},{"id":262,"symbol":"BTX","name":"Bitcore","circulatingSupply":16530732,"totalSupply":17290959,"rank":550,"type":"crypto"},{"id":217,"symbol":"BURST","name":"Burst","circulatingSupply":1999702438,"totalSupply":2158812800,"rank":536,"type":"crypto"},{"id":7040,"symbol":"BZE","name":"BZEdge","circulatingSupply":null,"totalSupply":null,"rank":4026,"type":"crypto"},{"id":10154,"symbol":"CALL","name":"Capital","circulatingSupply":null,"totalSupply":null,"rank":10656,"type":"crypto"},{"id":2205,"symbol":"CC","name":"CoinCollect","circulatingSupply":100000000,"totalSupply":100000000,"rank":7829,"type":"crypto"},{"id":988,"symbol":"CDN","name":"Canada eCoin","circulatingSupply":97415544,"totalSupply":100000000,"rank":1114,"type":"crypto"},{"id":323,"symbol":"CDT","name":"Blox","circulatingSupply":656173039,"totalSupply":1000000000,"rank":308,"type":"crypto"},{"id":72305,"symbol":"CHAIN","name":"Chainmakers","circulatingSupply":499999998.3071,"totalSupply":499999998.3071,"rank":3075,"type":"crypto"},{"id":1592,"symbol":"CHAT","name":"ChatCoin","circulatingSupply":null,"totalSupply":null,"rank":8170,"type":"crypto"},{"id":1897,"symbol":"CHIPS","name":"CHIPS","circulatingSupply":null,"totalSupply":null,"rank":2384,"type":"crypto"},{"id":5101,"symbol":"CIX","name":"Cryptonetix","circulatingSupply":100000000,"totalSupply":100000000,"rank":6420,"type":"crypto"},{"id":444,"symbol":"CLAM","name":"Clams","circulatingSupply":3307395,"totalSupply":16966894,"rank":2043,"type":"crypto"},{"id":279,"symbol":"CLOAK","name":"Cloakcoin","circulatingSupply":null,"totalSupply":null,"rank":2203,"type":"crypto"},{"id":5108,"symbol":"CMM","name":"Commercium","circulatingSupply":null,"totalSupply":null,"rank":6414,"type":"crypto"},{"id":1395,"symbol":"CMT","name":"Comet","circulatingSupply":778863938.7884,"totalSupply":1000000000,"rank":3049,"type":"crypto"},{"id":1614,"symbol":"CND","name":"Cindicator","circulatingSupply":2000000004.6079144,"totalSupply":2000000004.6079144,"rank":3002,"type":"crypto"},{"id":58,"symbol":"CNX","name":"Cryptonex","circulatingSupply":100000000,"totalSupply":100000000,"rank":62,"type":"crypto"},{"id":1508,"symbol":"CNY","name":"Chinese Yuan","circulatingSupply":1000000000,"totalSupply":1000000000,"rank":null,"type":"fiat"},{"id":330,"symbol":"COB","name":"Cobinhood","circulatingSupply":384592577,"totalSupply":1000000000,"rank":781,"type":"crypto"},{"id":753,"symbol":"COLX","name":"ColossusXT","circulatingSupply":10724738924,"totalSupply":10784272304,"rank":549,"type":"crypto"},{"id":2144,"symbol":"COMP","name":"Compound","circulatingSupply":null,"totalSupply":null,"rank":428,"type":"crypto"},{"id":null,"symbol":"COQUI","name":"COQUI Cash","circulatingSupply":null,"totalSupply":null,"rank":2000,"type":"crypto"},{"id":880,"symbol":"CRED","name":"Verify","circulatingSupply":33508864,"totalSupply":49997543,"rank":1339,"type":"crypto"},{"id":165,"symbol":"CRPT","name":"Crypterium","circulatingSupply":79436801.37187268,"totalSupply":99308004.00187267,"rank":235,"type":"crypto"},{"id":389,"symbol":"CRW","name":"Crown","circulatingSupply":20797848,"totalSupply":42000000,"rank":605,"type":"crypto"},{"id":196,"symbol":"CS","name":"CREDITS","circulatingSupply":null,"totalSupply":null,"rank":2368,"type":"crypto"},{"id":910,"symbol":"CTR","name":"Centra","circulatingSupply":67999999.5,"totalSupply":99999999.5,"rank":1299,"type":"crypto"},{"id":112,"symbol":"CTXC","name":"Cortex","circulatingSupply":10061553.96834451,"totalSupply":299792458,"rank":363,"type":"crypto"},{"id":118,"symbol":"CVC","name":"Civic","circulatingSupply":669995780.340009,"totalSupply":1000000000,"rank":127,"type":"crypto"},{"id":null,"symbol":"D","name":"Denarius","circulatingSupply":null,"totalSupply":null,"rank":2000,"type":"crypto"},{"id":68589,"symbol":"DAI","name":"Dai","circulatingSupply":1356940968.7218983,"totalSupply":1356941672.2833388,"rank":33,"type":"crypto"},{"id":13,"symbol":"DASH","name":"Dash","circulatingSupply":9925103.28316081,"totalSupply":9925103.28316081,"rank":36,"type":"crypto"},{"id":13,"symbol":"DASH","name":"Dash","circulatingSupply":9925103.28316081,"totalSupply":9925103.28316081,"rank":36,"type":"crypto"},{"id":1608,"symbol":"DAT","name":"Datum","circulatingSupply":100000000,"totalSupply":100000000,"rank":908,"type":"crypto"},{"id":177,"symbol":"DATA","name":"Streamr DATAcoin","circulatingSupply":677154514,"totalSupply":987154514,"rank":198,"type":"crypto"},{"id":308,"symbol":"DBC","name":"DeepBrain Chain","circulatingSupply":1500000000,"totalSupply":10000000000,"rank":370,"type":"crypto"},{"id":74,"symbol":"DCN","name":"Dentacoin","circulatingSupply":1322238425317,"totalSupply":8000000000000,"rank":269,"type":"crypto"},{"id":28,"symbol":"DCR","name":"Decred","circulatingSupply":12498459.86039943,"totalSupply":20999999.99800912,"rank":56,"type":"crypto"},{"id":null,"symbol":"DEEZ","name":"DeezNuts","circulatingSupply":null,"totalSupply":null,"rank":2000,"type":"crypto"},{"id":134,"symbol":"DENT","name":"Dent","circulatingSupply":88534462734.73587,"totalSupply":100000000000,"rank":214,"type":"crypto"},{"id":230,"symbol":"DEW","name":"DEW","circulatingSupply":103244553,"totalSupply":200000000,"rank":2288,"type":"crypto"},{"id":30,"symbol":"DGB","name":"DigiByte","circulatingSupply":13950623574.446024,"totalSupply":13950623574.446024,"rank":77,"type":"crypto"},{"id":84,"symbol":"DGD","name":"DigixDAO","circulatingSupply":144763.85994680802,"totalSupply":1999999.9966,"rank":199,"type":"crypto"},{"id":1593,"symbol":"DLT","name":"Agrello","circulatingSupply":130271020.035721,"totalSupply":130271020.035721,"rank":3092,"type":"crypto"},{"id":245,"symbol":"DNT","name":"district0x","circulatingSupply":600000000,"totalSupply":1000000000,"rank":149,"type":"crypto"},{"id":368,"symbol":"DOCK","name":"Dock","circulatingSupply":433052635,"totalSupply":1000000000,"rank":262,"type":"crypto"},{"id":20,"symbol":"DOGE","name":"Dogecoin","circulatingSupply":127983817442.4694,"totalSupply":127983817442.4694,"rank":38,"type":"crypto"},{"id":574,"symbol":"DOT","name":"Polkadot","circulatingSupply":312018000,"totalSupply":890000000,"rank":1704,"type":"crypto"},{"id":109,"symbol":"DRGN","name":"Dragonchain","circulatingSupply":433207044.4587562,"totalSupply":433494437,"rank":473,"type":"crypto"},{"id":88,"symbol":"DROP","name":"Dropil","circulatingSupply":22935612033.26666,"totalSupply":30000000000,"rank":1340,"type":"crypto"},{"id":192,"symbol":"DTA","name":"DATA","circulatingSupply":7255189844,"totalSupply":11500000000,"rank":338,"type":"crypto"},{"id":687,"symbol":"DTH","name":"Dether","circulatingSupply":83600000,"totalSupply":100000000,"rank":654,"type":"crypto"},{"id":275,"symbol":"DTR","name":"Dynamic Trading Rights","circulatingSupply":55694875,"totalSupply":1900000000,"rank":380,"type":"crypto"},{"id":861,"symbol":"EBST","name":"eBoost","circulatingSupply":20000000,"totalSupply":80828160,"rank":966,"type":"crypto"},{"id":258,"symbol":"ECA","name":"Electra","circulatingSupply":28352206010,"totalSupply":29219362563,"rank":705,"type":"crypto"},{"id":236,"symbol":"EDG","name":"Edgeless","circulatingSupply":97818696,"totalSupply":132046997,"rank":359,"type":"crypto"},{"id":151,"symbol":"EDO","name":"Eidoo","circulatingSupply":26835711.19291738,"totalSupply":59634176.06725173,"rank":752,"type":"crypto"},{"id":4526,"symbol":"EDOGE","name":"EtherDoge","circulatingSupply":1.0000000100005e+23,"totalSupply":1.000000010001e+23,"rank":6672,"type":"crypto"},{"id":90,"symbol":"ELA","name":"Elastos","circulatingSupply":9599802,"totalSupply":33777123,"rank":217,"type":"crypto"},{"id":1830,"symbol":"ELEC","name":"Electrify.Asia","circulatingSupply":749999753.1986161,"totalSupply":749999945.2724185,"rank":721,"type":"crypto"},{"id":69,"symbol":"ELF","name":"aelf","circulatingSupply":864213921.7547559,"totalSupply":879999999.9864658,"rank":121,"type":"crypto"},{"id":800,"symbol":"ELIX","name":"Elixir","circulatingSupply":35516245.219311796,"totalSupply":35516245.219311796,"rank":1441,"type":"crypto"},{"id":913,"symbol":"ELLA","name":"Ellaism","circulatingSupply":null,"totalSupply":null,"rank":1292,"type":"crypto"},{"id":119,"symbol":"EMC","name":"EmerCoin","circulatingSupply":42118422,"totalSupply":1000000000,"rank":568,"type":"crypto"},{"id":207,"symbol":"EMC2","name":"Einsteinium","circulatingSupply":217904165,"totalSupply":299792458,"rank":227,"type":"crypto"},{"id":113,"symbol":"ENG","name":"Enigma","circulatingSupply":13396935.056720179,"totalSupply":150000000,"rank":333,"type":"crypto"},{"id":126,"symbol":"ENJ","name":"Enjin Coin","circulatingSupply":761158535,"totalSupply":1000000000,"rank":97,"type":"crypto"},{"id":4858,"symbol":"ENTRP","name":"Hut34 Entropy","circulatingSupply":100000000,"totalSupply":100000000,"rank":3060,"type":"crypto"},{"id":5220,"symbol":"EON","name":"EOS Network","circulatingSupply":null,"totalSupply":null,"rank":6324,"type":"crypto"},{"id":6997,"symbol":"EOP","name":"EOP","circulatingSupply":null,"totalSupply":null,"rank":4067,"type":"crypto"},{"id":5,"symbol":"EOS","name":"EOS","circulatingSupply":929974540.3942999,"totalSupply":1026270178.1981,"rank":19,"type":"crypto"},{"id":10755,"symbol":"EQLI","name":"Equaliser","circulatingSupply":null,"totalSupply":null,"rank":10171,"type":"crypto"},{"id":4533,"symbol":"EQUA","name":"EQUA","circulatingSupply":999991534.8289,"totalSupply":999999462.6499,"rank":475,"type":"crypto"},{"id":16,"symbol":"ETC","name":"Ethereum Classic","circulatingSupply":116313299,"totalSupply":107988299,"rank":50,"type":"crypto"},{"id":2,"symbol":"ETH","name":"Ethereum","circulatingSupply":113818737.6164244,"totalSupply":114298549.0615,"rank":2,"type":"crypto"},{"id":158,"symbol":"ETHOS","name":"Ethos","circulatingSupply":82358464.23845324,"totalSupply":222295208.23845324,"rank":131,"type":"crypto"},{"id":47,"symbol":"ETN","name":"Electroneum","circulatingSupply":7980960914,"totalSupply":8343399791,"rank":170,"type":"crypto"},{"id":48,"symbol":"ETP","name":"Metaverse ETP","circulatingSupply":53567778,"totalSupply":56901911,"rank":291,"type":"crypto"},{"id":1561,"symbol":"EUR","name":"Euro","circulatingSupply":13211083.4,"totalSupply":13211083.4,"rank":null,"type":"fiat"},{"id":363,"symbol":"EVX","name":"Everex","circulatingSupply":16500000,"totalSupply":25000000,"rank":299,"type":"crypto"},{"id":null,"symbol":"EXMO","name":"EXMO","circulatingSupply":null,"totalSupply":null,"rank":2000,"type":"crypto"},{"id":636,"symbol":"EXP","name":"Expanse","circulatingSupply":10495278,"totalSupply":19495278,"rank":735,"type":"crypto"},{"id":1113,"symbol":"FAIR","name":"Faircoin","circulatingSupply":null,"totalSupply":null,"rank":434,"type":"crypto"},{"id":129,"symbol":"FCT","name":"Factom","circulatingSupply":8745102,"totalSupply":8753873,"rank":493,"type":"crypto"},{"id":74500,"symbol":"FIL","name":"Filecoin [IOU]","circulatingSupply":44584205,"totalSupply":null,"rank":42,"type":"crypto"},{"id":998,"symbol":"FJC","name":"Fujicoin","circulatingSupply":null,"totalSupply":null,"rank":1107,"type":"crypto"},{"id":682,"symbol":"FLDC","name":"Foldingcoin","circulatingSupply":696185238,"totalSupply":1000000000,"rank":519,"type":"crypto"},{"id":532,"symbol":"FLO","name":"FLO","circulatingSupply":145710343,"totalSupply":160000000,"rank":601,"type":"crypto"},{"id":null,"symbol":"FSN","name":"FUSION","circulatingSupply":null,"totalSupply":null,"rank":2000,"type":"crypto"},{"id":359,"symbol":"FTC","name":"Feathercoin","circulatingSupply":217664440,"totalSupply":336000000,"rank":563,"type":"crypto"},{"id":352,"symbol":"FUEL","name":"Etherparty","circulatingSupply":528478202,"totalSupply":1000000000,"rank":869,"type":"crypto"},{"id":80,"symbol":"FUN","name":"FunFair","circulatingSupply":6548861175.662673,"totalSupply":10999873621.398026,"rank":119,"type":"crypto"},{"id":290,"symbol":"GAME","name":"GameCredits","circulatingSupply":184374289,"totalSupply":200000000,"rank":498,"type":"crypto"},{"id":102,"symbol":"GAS","name":"Gas","circulatingSupply":96263640.8017974,"totalSupply":100000000,"rank":101,"type":"crypto"},{"id":2187,"symbol":"GBP","name":"Pound","circulatingSupply":null,"totalSupply":null,"rank":null,"type":"fiat"},{"id":637,"symbol":"GBX","name":"Globitex","circulatingSupply":2950298,"totalSupply":31800000,"rank":925,"type":"crypto"},{"id":148,"symbol":"GBYTE","name":"Obyte","circulatingSupply":662811,"totalSupply":1000000,"rank":482,"type":"crypto"},{"id":null,"symbol":"GENERIC","name":"GENERIC","circulatingSupply":null,"totalSupply":null,"rank":2000,"type":"crypto"},{"id":341,"symbol":"GIN","name":"GINcoin","circulatingSupply":4995980,"totalSupply":5000000,"rank":1036,"type":"crypto"},{"id":null,"symbol":"GLXT","name":"GLX Token","circulatingSupply":null,"totalSupply":null,"rank":2000,"type":"crypto"},{"id":4561,"symbol":"GMR","name":"Gimmer","circulatingSupply":null,"totalSupply":null,"rank":6658,"type":"crypto"},{"id":178,"symbol":"GNO","name":"Gnosis","circulatingSupply":1104590,"totalSupply":10000000,"rank":116,"type":"crypto"},{"id":49,"symbol":"GNT","name":"Golem","circulatingSupply":561908291.8712766,"totalSupply":645000608.6462615,"rank":143,"type":"crypto"},{"id":3256,"symbol":"GOLD","name":"Dragonereum Gold","circulatingSupply":null,"totalSupply":null,"rank":7125,"type":"crypto"},{"id":485,"symbol":"GRC","name":"Gridcoin","circulatingSupply":null,"totalSupply":null,"rank":1863,"type":"crypto"},{"id":10107,"symbol":"GRIN","name":"Grin","circulatingSupply":null,"totalSupply":62899200,"rank":220,"type":"crypto"},{"id":123,"symbol":"GRS","name":"Groestlcoin","circulatingSupply":71310189,"totalSupply":105000000,"rank":211,"type":"crypto"},{"id":534,"symbol":"GSC","name":"Global Social Chain","circulatingSupply":461460428,"totalSupply":1000000000,"rank":358,"type":"crypto"},{"id":135,"symbol":"GTO","name":"Gifto","circulatingSupply":531819169,"totalSupply":1000000000,"rank":266,"type":"crypto"},{"id":539,"symbol":"GUP","name":"Guppy","circulatingSupply":73855149.62,"totalSupply":98855149.62,"rank":1757,"type":"crypto"},{"id":1630,"symbol":"GUSD","name":"Gemini dollar","circulatingSupply":42492396.43,"totalSupply":42492396.43,"rank":173,"type":"crypto"},{"id":108,"symbol":"GVT","name":"Genesis Vision","circulatingSupply":4419078.51188056,"totalSupply":4436643.928533333,"rank":262,"type":"crypto"},{"id":70,"symbol":"GXS","name":"GXChain","circulatingSupply":60000000,"totalSupply":100000000,"rank":223,"type":"crypto"},{"id":null,"symbol":"GZR","name":"Gizer","circulatingSupply":null,"totalSupply":null,"rank":2000,"type":"crypto"},{"id":5336,"symbol":"HIGHT","name":"Highcoin","circulatingSupply":null,"totalSupply":null,"rank":6223,"type":"crypto"},{"id":1083,"symbol":"HODL","name":"HOdlcoin","circulatingSupply":232524610,"totalSupply":250000000,"rank":2847,"type":"crypto"},{"id":1886,"symbol":"HOT","name":"Holo","circulatingSupply":404505834.8724246,"totalSupply":1560000000,"rank":391,"type":"crypto"},{"id":157,"symbol":"HPB","name":"High Performance Blockchain","circulatingSupply":37302632,"totalSupply":100000000,"rank":317,"type":"crypto"},{"id":null,"symbol":"HSR","name":"HShare","circulatingSupply":null,"totalSupply":null,"rank":2000,"type":"crypto"},{"id":71,"symbol":"HT","name":"HOTTO","circulatingSupply":191611326.3544121,"totalSupply":500000000,"rank":45,"type":"crypto"},{"id":396,"symbol":"HTML","name":"HTMLCOIN","circulatingSupply":53067332240,"totalSupply":80434575000,"rank":582,"type":"crypto"},{"id":882,"symbol":"HUC","name":"Huntercoin","circulatingSupply":23761750,"totalSupply":42000000,"rank":1336,"type":"crypto"},{"id":983,"symbol":"HUSH","name":"Hush","circulatingSupply":5182075,"totalSupply":21000000,"rank":1118,"type":"crypto"},{"id":130,"symbol":"ICN","name":"Iconomi","circulatingSupply":99999909,"totalSupply":100000000,"rank":2670,"type":"crypto"},{"id":37,"symbol":"ICX","name":"ICON","circulatingSupply":523834817,"totalSupply":800460000,"rank":79,"type":"crypto"},{"id":218,"symbol":"IGNIS","name":"Ignis","circulatingSupply":440000000,"totalSupply":999449694,"rank":238,"type":"crypto"},{"id":5366,"symbol":"ILK","name":"Inlock Token","circulatingSupply":null,"totalSupply":null,"rank":6196,"type":"crypto"},{"id":374,"symbol":"INK","name":"Ink","circulatingSupply":463910527,"totalSupply":1000000000,"rank":721,"type":"crypto"},{"id":246,"symbol":"INS","name":"Insolar","circulatingSupply":32500000,"totalSupply":50000000,"rank":508,"type":"crypto"},{"id":269,"symbol":"ION","name":"ION","circulatingSupply":21242460,"totalSupply":50900000,"rank":813,"type":"crypto"},{"id":762,"symbol":"IOP","name":"Internet of People","circulatingSupply":5368675,"totalSupply":21000000,"rank":746,"type":"crypto"},{"id":61,"symbol":"IOST","name":"IOStoken","circulatingSupply":22312034727.470333,"totalSupply":22312034727.470333,"rank":60,"type":"crypto"},{"id":204,"symbol":"IOTX","name":"IoTeX","circulatingSupply":1331040005,"totalSupply":10000000000,"rank":259,"type":"crypto"},{"id":107,"symbol":"IQ","name":"Everipedia","circulatingSupply":10000000000,"totalSupply":10000000000,"rank":192,"type":"crypto"},{"id":240,"symbol":"ITC","name":"IoT Chain","circulatingSupply":62617239,"totalSupply":100000000,"rank":331,"type":"crypto"},{"id":1318,"symbol":"JNT","name":"Jibrel Network","circulatingSupply":551050,"totalSupply":200000000,"rank":408,"type":"crypto"},{"id":1520,"symbol":"JPY","name":"Japanese Yen","circulatingSupply":null,"totalSupply":null,"rank":null,"type":"fiat"},{"id":62,"symbol":"KCS","name":"KuCoin Shares","circulatingSupply":80118638,"totalSupply":170118638,"rank":133,"type":"crypto"},{"id":115,"symbol":"KIN","name":"Kin","circulatingSupply":1675683603427,"totalSupply":null,"rank":151,"type":"crypto"},{"id":63056,"symbol":"KLOWN","name":"Ether Clown","circulatingSupply":70754.6484634,"totalSupply":125559.7484621,"rank":5329,"type":"crypto"},{"id":57,"symbol":"KMD","name":"Komodo","circulatingSupply":110651899,"totalSupply":200000000,"rank":152,"type":"crypto"},{"id":104,"symbol":"KNC","name":"Kyber Network","circulatingSupply":201317421.09473535,"totalSupply":210325273.09255603,"rank":89,"type":"crypto"},{"id":902,"symbol":"KRB","name":"Karbo","circulatingSupply":5385223,"totalSupply":10000000,"rank":727,"type":"crypto"},{"id":364,"symbol":"LBC","name":"LBRY Credits","circulatingSupply":205956716,"totalSupply":1000000000,"rank":221,"type":"crypto"},{"id":227,"symbol":"LEND","name":"ETHLend","circulatingSupply":1297499222.6810105,"totalSupply":1299999941.7031682,"rank":2925,"type":"crypto"},{"id":284,"symbol":"LEO","name":"Unus Sed LEO","circulatingSupply":101743211,"totalSupply":1000000000,"rank":2191,"type":"crypto"},{"id":59,"symbol":"LINK","name":"ChainLink","circulatingSupply":401509550.91374743,"totalSupply":1000000000,"rank":8,"type":"crypto"},{"id":298,"symbol":"LKK","name":"Lykke","circulatingSupply":316809739,"totalSupply":1285690000,"rank":558,"type":"crypto"},{"id":79,"symbol":"LOOM","name":"Loom Network","circulatingSupply":970520752.7152581,"totalSupply":1000000000,"rank":165,"type":"crypto"},{"id":5453,"symbol":"LPT","name":"Livepeer Token","circulatingSupply":null,"totalSupply":null,"rank":6126,"type":"crypto"},{"id":72,"symbol":"LRC","name":"Loopring","circulatingSupply":874773407.4179802,"totalSupply":1395076054.5238578,"rank":78,"type":"crypto"},{"id":27,"symbol":"LSK","name":"Lisk","circulatingSupply":126942926.24911062,"totalSupply":142966198,"rank":102,"type":"crypto"},{"id":7,"symbol":"LTC","name":"Litecoin","circulatingSupply":66808745.73346589,"totalSupply":66808745.73347135,"rank":7,"type":"crypto"},{"id":346,"symbol":"LUN","name":"Lunyr","circulatingSupply":2297853.0785315786,"totalSupply":2703356.0785315786,"rank":752,"type":"crypto"},{"id":64,"symbol":"MAID","name":"MaidSafeCoin","circulatingSupply":452552411.9996774,"totalSupply":452552412,"rank":114,"type":"crypto"},{"id":77,"symbol":"MANA","name":"Decentraland","circulatingSupply":2061999221.0223563,"totalSupply":2194939927.320146,"rank":91,"type":"crypto"},{"id":12606,"symbol":"MATIC","name":"Matic Network","circulatingSupply":4864264323.089596,"totalSupply":10000000000,"rank":104,"type":"crypto"},{"id":1329,"symbol":"MCAP","name":"MCAP","circulatingSupply":10490000,"totalSupply":100000000,"rank":2647,"type":"crypto"},{"id":89,"symbol":"MCO","name":"Crypto.com","circulatingSupply":15793831.3632061,"totalSupply":31587682.3632061,"rank":171,"type":"crypto"},{"id":144,"symbol":"MDA","name":"Moeda Loyalty Points","circulatingSupply":19628888,"totalSupply":19628888,"rank":258,"type":"crypto"},{"id":210,"symbol":"MDS","name":"MediShares","circulatingSupply":1031355785,"totalSupply":2000000000,"rank":334,"type":"crypto"},{"id":1413,"symbol":"MED","name":"Medibloc","circulatingSupply":100000000,"totalSupply":100000000,"rank":2578,"type":"crypto"},{"id":2099,"symbol":"MEETONE","name":"MEET.ONE","circulatingSupply":null,"totalSupply":null,"rank":7892,"type":"crypto"},{"id":171,"symbol":"MFT","name":"Mainframe","circulatingSupply":3937700694,"totalSupply":10000000000,"rank":248,"type":"crypto"},{"id":12,"symbol":"MIOTA","name":"IOTA","circulatingSupply":2779530283,"totalSupply":2779530283,"rank":37,"type":"crypto"},{"id":63,"symbol":"MITH","name":"Mithril","circulatingSupply":848914277.4594778,"totalSupply":1000000000,"rank":278,"type":"crypto"},{"id":22,"symbol":"MKR","name":"Maker","circulatingSupply":902293.2147348671,"totalSupply":995849.4035139839,"rank":35,"type":"crypto"},{"id":427,"symbol":"MLN","name":"Melon","circulatingSupply":997400,"totalSupply":1250000,"rank":185,"type":"crypto"},{"id":312,"symbol":"MNX","name":"MinexCoin","circulatingSupply":4486889,"totalSupply":6066798,"rank":946,"type":"crypto"},{"id":4398,"symbol":"MNZ","name":"MNZ","circulatingSupply":null,"totalSupply":null,"rank":6750,"type":"crypto"},{"id":68,"symbol":"MOAC","name":"MOAC","circulatingSupply":62463334,"totalSupply":151205864,"rank":551,"type":"crypto"},{"id":242,"symbol":"MOD","name":"Modum","circulatingSupply":15266200,"totalSupply":21266200,"rank":471,"type":"crypto"},{"id":75,"symbol":"MONA","name":"MonaCoin","circulatingSupply":63703750,"totalSupply":105120000,"rank":126,"type":"crypto"},{"id":695,"symbol":"MSR","name":"Masari","circulatingSupply":8267551,"totalSupply":18500000,"rank":882,"type":"crypto"},{"id":390,"symbol":"MTH","name":"Monetha","circulatingSupply":218271923,"totalSupply":402400000,"rank":350,"type":"crypto"},{"id":184,"symbol":"MTL","name":"Metal","circulatingSupply":32515288,"totalSupply":66588888,"rank":243,"type":"crypto"},{"id":503,"symbol":"MUSIC","name":"Musicoin","circulatingSupply":null,"totalSupply":null,"rank":1814,"type":"crypto"},{"id":3419,"symbol":"MZC","name":"MAZA","circulatingSupply":1055345280,"totalSupply":2419200000,"rank":2126,"type":"crypto"},{"id":35,"symbol":"NANO","name":"Nano","circulatingSupply":133248289,"totalSupply":133248289,"rank":63,"type":"crypto"},{"id":67,"symbol":"NAS","name":"Nebulas","circulatingSupply":45500000,"totalSupply":100000000,"rank":241,"type":"crypto"},{"id":215,"symbol":"NAV","name":"NavCoin","circulatingSupply":70749418.90771085,"totalSupply":70749418.90771085,"rank":249,"type":"crypto"},{"id":164,"symbol":"NCASH","name":"Nucleus Vision","circulatingSupply":5500052915,"totalSupply":10000000000,"rank":301,"type":"crypto"},{"id":null,"symbol":"NDZ","name":"NDZ","circulatingSupply":null,"totalSupply":null,"rank":2000,"type":"crypto"},{"id":162,"symbol":"NEBL","name":"Neblio","circulatingSupply":13734385,"totalSupply":14485740,"rank":245,"type":"crypto"},{"id":15,"symbol":"NEO","name":"NEO","circulatingSupply":72199696,"totalSupply":100000000,"rank":30,"type":"crypto"},{"id":707,"symbol":"NEOS","name":"Neoscoin","circulatingSupply":4114781,"totalSupply":21000000,"rank":1578,"type":"crypto"},{"id":307,"symbol":"NEU","name":"Neumark","circulatingSupply":66352296.087325245,"totalSupply":66352296.087325245,"rank":500,"type":"crypto"},{"id":99,"symbol":"NEXO","name":"Nexo","circulatingSupply":646145840.9989921,"totalSupply":1000000000,"rank":69,"type":"crypto"},{"id":237,"symbol":"NGC","name":"NAGA","circulatingSupply":59420636,"totalSupply":77910266,"rank":546,"type":"crypto"},{"id":613,"symbol":"NIO","name":"Autonio","circulatingSupply":82820804,"totalSupply":220466789,"rank":1671,"type":"crypto"},{"id":552,"symbol":"NLC2","name":"NoLimitCoin","circulatingSupply":null,"totalSupply":null,"rank":1739,"type":"crypto"},{"id":321,"symbol":"NLG","name":"Gulden","circulatingSupply":415032420,"totalSupply":1680000000,"rank":514,"type":"crypto"},{"id":234,"symbol":"NMC","name":"Namecoin","circulatingSupply":14736400,"totalSupply":21000000,"rank":489,"type":"crypto"},{"id":422,"symbol":"NMR","name":"Numeraire","circulatingSupply":9987656.009716481,"totalSupply":10974157.537253253,"rank":85,"type":"crypto"},{"id":44,"symbol":"NPXS","name":"Pundi X","circulatingSupply":236403522004.825,"totalSupply":258498693019.06998,"rank":137,"type":"crypto"},{"id":111,"symbol":"NULS","name":"Nuls","circulatingSupply":728627.6862145662,"totalSupply":40000000,"rank":398,"type":"crypto"},{"id":116,"symbol":"NXS","name":"Nexus","circulatingSupply":59707886,"totalSupply":78000000,"rank":232,"type":"crypto"},{"id":94,"symbol":"NXT","name":"NXT","circulatingSupply":998999942,"totalSupply":1000000000,"rank":255,"type":"crypto"},{"id":394,"symbol":"OAX","name":"OpenANX","circulatingSupply":25009250,"totalSupply":100000000,"rank":332,"type":"crypto"},{"id":633,"symbol":"OK","name":"OKCash","circulatingSupply":74258651,"totalSupply":105000000,"rank":584,"type":"crypto"},{"id":24,"symbol":"OMG","name":"OMG Network","circulatingSupply":140231632.825095,"totalSupply":140245398.24513277,"rank":57,"type":"crypto"},{"id":611,"symbol":"OMNI","name":"Omni","circulatingSupply":619140.82280913,"totalSupply":619140.82280913,"rank":343,"type":"crypto"},{"id":141,"symbol":"ONG","name":"SoMee.Social","circulatingSupply":191336897,"totalSupply":300000000,"rank":2581,"type":"crypto"},{"id":26,"symbol":"ONT","name":"Ontology","circulatingSupply":637351170,"totalSupply":1000000000,"rank":67,"type":"crypto"},{"id":990,"symbol":"OOT","name":"Utrum","circulatingSupply":32400071,"totalSupply":216000091,"rank":874,"type":"crypto"},{"id":285,"symbol":"OST","name":"OST","circulatingSupply":288515753,"totalSupply":800000000,"rank":313,"type":"crypto"},{"id":285,"symbol":"OST","name":"OST","circulatingSupply":288515753,"totalSupply":800000000,"rank":313,"type":"crypto"},{"id":3845,"symbol":"OX","name":"OX Fina","circulatingSupply":null,"totalSupply":null,"rank":6939,"type":"crypto"},{"id":64962,"symbol":"OXT","name":"Orchid","circulatingSupply":1000000000,"totalSupply":1000000000,"rank":83,"type":"crypto"},{"id":187,"symbol":"PART","name":"Particl","circulatingSupply":8979383.9002939,"totalSupply":9749721.0094204,"rank":520,"type":"crypto"},{"id":351,"symbol":"PASC","name":"Pascalcoin","circulatingSupply":null,"totalSupply":null,"rank":2122,"type":"crypto"},{"id":1228,"symbol":"PASL","name":"Pascal Lite","circulatingSupply":null,"totalSupply":null,"rank":2726,"type":"crypto"},{"id":1694,"symbol":"PAX","name":"PAX Token","circulatingSupply":468289789.96,"totalSupply":468289789.96,"rank":59,"type":"crypto"},{"id":91,"symbol":"PAY","name":"TenX","circulatingSupply":205218255.94457775,"totalSupply":205218255.94857776,"rank":263,"type":"crypto"},{"id":835,"symbol":"PAYX","name":"Paypex","circulatingSupply":68428768,"totalSupply":150000000,"rank":1063,"type":"crypto"},{"id":648,"symbol":"PINK","name":"Pinkcoin","circulatingSupply":391862313,"totalSupply":500000000,"rank":641,"type":"crypto"},{"id":621,"symbol":"PIRL","name":"Pirl","circulatingSupply":null,"totalSupply":null,"rank":1667,"type":"crypto"},{"id":93,"symbol":"PIVX","name":"PIVX","circulatingSupply":63261755,"totalSupply":63261755,"rank":207,"type":"crypto"},{"id":145,"symbol":"PLR","name":"Pillar","circulatingSupply":259348201,"totalSupply":800000000,"rank":527,"type":"crypto"},{"id":222,"symbol":"POA","name":"POA Network","circulatingSupply":220167290,"totalSupply":258036410,"rank":307,"type":"crypto"},{"id":179,"symbol":"POE","name":"Po.et","circulatingSupply":2397663513,"totalSupply":3141592653,"rank":715,"type":"crypto"},{"id":544,"symbol":"POLIS","name":"Polis","circulatingSupply":4262523,"totalSupply":25000000,"rank":546,"type":"crypto"},{"id":101,"symbol":"POLY","name":"Polymath Network","circulatingSupply":718771208.3677331,"totalSupply":1000000000,"rank":150,"type":"crypto"},{"id":468,"symbol":"POT","name":"Potcoin","circulatingSupply":221084536,"totalSupply":420000000,"rank":555,"type":"crypto"},{"id":92,"symbol":"POWR","name":"Power Ledger","circulatingSupply":952875970.28937,"totalSupply":1000000000,"rank":124,"type":"crypto"},{"id":176,"symbol":"PPC","name":"Peercoin","circulatingSupply":26088476,"totalSupply":26088476,"rank":491,"type":"crypto"},{"id":318,"symbol":"PPP","name":"PayPie","circulatingSupply":82500000,"totalSupply":165000000,"rank":438,"type":"crypto"},{"id":54,"symbol":"PPT","name":"Populous","circulatingSupply":53252006.99438964,"totalSupply":53252246,"rank":168,"type":"crypto"},{"id":338,"symbol":"PRE","name":"Presearch","circulatingSupply":null,"totalSupply":null,"rank":2129,"type":"crypto"},{"id":430,"symbol":"PRL","name":"Oyster","circulatingSupply":58898030.79730333,"totalSupply":104223796.79730333,"rank":2062,"type":"crypto"},{"id":null,"symbol":"PUNGO","name":"Pungo Token","circulatingSupply":null,"totalSupply":null,"rank":2000,"type":"crypto"},{"id":438,"symbol":"PURA","name":"Pura","circulatingSupply":174840572,"totalSupply":181623066,"rank":2053,"type":"crypto"},{"id":83,"symbol":"QASH","name":"QASH","circulatingSupply":349999989.25029397,"totalSupply":1000000000,"rank":250,"type":"crypto"},{"id":null,"symbol":"QIWI","name":"QIWI","circulatingSupply":null,"totalSupply":null,"rank":2000,"type":"crypto"},{"id":281,"symbol":"QLC","name":"QLC Chain","circulatingSupply":240000000,"totalSupply":600000000,"rank":321,"type":"crypto"},{"id":297,"symbol":"QRL","name":"Quantum Resistant Ledger","circulatingSupply":12000000,"totalSupply":65000000,"rank":574,"type":"crypto"},{"id":188,"symbol":"QSP","name":"Quantstamp","circulatingSupply":617314171.3211849,"totalSupply":976442388.3211849,"rank":237,"type":"crypto"},{"id":29,"symbol":"QTUM","name":"Qtum","circulatingSupply":103084616,"totalSupply":103084616,"rank":80,"type":"crypto"},{"id":114,"symbol":"R","name":"Revain","circulatingSupply":60550308334.001625,"totalSupply":60550308334.001625,"rank":55,"type":"crypto"},{"id":483,"symbol":"RADS","name":"Radium","circulatingSupply":3562285,"totalSupply":9000000,"rank":1866,"type":"crypto"},{"id":5661,"symbol":"RAP","name":"Rapture","circulatingSupply":null,"totalSupply":null,"rank":5950,"type":"crypto"},{"id":255,"symbol":"RCN","name":"Rcoin","circulatingSupply":497530791.35309,"totalSupply":999942647.35309,"rank":219,"type":"crypto"},{"id":65,"symbol":"RDD","name":"Reddcoin","circulatingSupply":29940302496.525364,"totalSupply":null,"rank":177,"type":"crypto"},{"id":163,"symbol":"RDN","name":"Raiden Network Token","circulatingSupply":99999999.99508187,"totalSupply":99999999.99999996,"rank":234,"type":"crypto"},{"id":229,"symbol":"REN","name":"Ren","circulatingSupply":601586967,"totalSupply":999999632.80375,"rank":74,"type":"crypto"},{"id":50,"symbol":"REP","name":"Augur","circulatingSupply":5778166.84125945,"totalSupply":5778166.84125945,"rank":115,"type":"crypto"},{"id":null,"symbol":"REPV2","name":"Augur","circulatingSupply":null,"totalSupply":null,"rank":2000,"type":"crypto"},{"id":137,"symbol":"REQ","name":"Request","circulatingSupply":729637720.1960433,"totalSupply":999912165.4980812,"rank":218,"type":"crypto"},{"id":81,"symbol":"RHOC","name":"RChain","circulatingSupply":792479301.8165612,"totalSupply":1000000000,"rank":1429,"type":"crypto"},{"id":2976,"symbol":"RIC","name":"Riecoin","circulatingSupply":44344375,"totalSupply":84000000,"rank":2170,"type":"crypto"},{"id":404,"symbol":"RISE","name":"Rise","circulatingSupply":null,"totalSupply":null,"rank":2086,"type":"crypto"},{"id":147,"symbol":"RLC","name":"iExec RLC","circulatingSupply":80070577.9868455,"totalSupply":86999784.9868455,"rank":132,"type":"crypto"},{"id":null,"symbol":"RPX","name":"RPX","circulatingSupply":null,"totalSupply":null,"rank":2000,"type":"crypto"},{"id":2776,"symbol":"RUB","name":"Russian Ruble","circulatingSupply":1487124821,"totalSupply":1487124821,"rank":null,"type":"fiat"},{"id":125,"symbol":"RVN","name":"Ravencoin","circulatingSupply":7933955000,"totalSupply":21000000000,"rank":109,"type":"crypto"},{"id":2168,"symbol":"RYO","name":"Ryo Currency","circulatingSupply":26766160.10310119,"totalSupply":26766160.10310119,"rank":814,"type":"crypto"},{"id":4226,"symbol":"SAFE","name":"Safe","circulatingSupply":null,"totalSupply":null,"rank":6859,"type":"crypto"},{"id":4673,"symbol":"SAI","name":"Single Collateral DAI","circulatingSupply":220180.8801341085,"totalSupply":220180.8801341085,"rank":1015,"type":"crypto"},{"id":122,"symbol":"SALT","name":"SALT","circulatingSupply":92637056.20902027,"totalSupply":120000000,"rank":186,"type":"crypto"},{"id":154,"symbol":"SAN","name":"Santiment Network Token","circulatingSupply":62660371,"totalSupply":83337000,"rank":532,"type":"crypto"},{"id":233,"symbol":"SBD","name":"Steem Dollars","circulatingSupply":5977864.204,"totalSupply":null,"rank":233,"type":"crypto"},{"id":null,"symbol":"SBERBANK","name":"SBERBANK","circulatingSupply":null,"totalSupply":null,"rank":2000,"type":"crypto"},{"id":38,"symbol":"SC","name":"Siacoin","circulatingSupply":45317182992,"totalSupply":44972692992,"rank":95,"type":"crypto"},{"id":388,"symbol":"SHIFT","name":"Shift","circulatingSupply":null,"totalSupply":null,"rank":2099,"type":"crypto"},{"id":617,"symbol":"SIB","name":"SIBCoin","circulatingSupply":17160310,"totalSupply":24000000,"rank":746,"type":"crypto"},{"id":14196,"symbol":"SIN","name":"SINOVATE","circulatingSupply":null,"totalSupply":null,"rank":8632,"type":"crypto"},{"id":128,"symbol":"SKY","name":"Skycoin","circulatingSupply":9999999,"totalSupply":100000000,"rank":298,"type":"crypto"},{"id":548,"symbol":"SLR","name":"Solarcoin","circulatingSupply":48952465,"totalSupply":98100000000,"rank":662,"type":"crypto"},{"id":220,"symbol":"SLS","name":"SaluS","circulatingSupply":null,"totalSupply":null,"rank":2302,"type":"crypto"},{"id":168,"symbol":"SMART","name":"SmartCash","circulatingSupply":171249.17390414,"totalSupply":2014903577,"rank":1084,"type":"crypto"},{"id":168,"symbol":"SMART","name":"SmartCash","circulatingSupply":171249.17390414,"totalSupply":2014903577,"rank":1084,"type":"crypto"},{"id":257,"symbol":"SNGLS","name":"SingularDTV","circulatingSupply":600000000,"totalSupply":1000000000,"rank":324,"type":"crypto"},{"id":214,"symbol":"SNM","name":"SONM","circulatingSupply":359600000,"totalSupply":444000000,"rank":326,"type":"crypto"},{"id":53,"symbol":"SNT","name":"Status","circulatingSupply":3880483784.187866,"totalSupply":6804870174.878169,"rank":94,"type":"crypto"},{"id":190,"symbol":"SOC","name":"All Sports","circulatingSupply":1466525363,"totalSupply":1500000000,"rank":537,"type":"crypto"},{"id":253,"symbol":"SPHTX","name":"SophiaTX","circulatingSupply":193230567,"totalSupply":350000000,"rank":897,"type":"crypto"},{"id":213,"symbol":"SRN","name":"Sirin Labs Token","circulatingSupply":491820906,"totalSupply":572166104,"rank":256,"type":"crypto"},{"id":1037,"symbol":"STAK","name":"STRAKS","circulatingSupply":9653106,"totalSupply":150000000,"rank":973,"type":"crypto"},{"id":1134,"symbol":"START","name":"Startcoin","circulatingSupply":45079785,"totalSupply":70782220,"rank":2800,"type":"crypto"},{"id":39,"symbol":"STEEM","name":"Steem","circulatingSupply":375764836.082,"totalSupply":408430760.694,"rank":148,"type":"crypto"},{"id":121,"symbol":"STORJ","name":"Storj","circulatingSupply":405256130.4226285,"totalSupply":424999998.00001335,"rank":108,"type":"crypto"},{"id":136,"symbol":"STORM","name":"Storm","circulatingSupply":4518781114,"totalSupply":433211184.0771866,"rank":474,"type":"crypto"},{"id":169,"symbol":"STQ","name":"Storiqa","circulatingSupply":9820877589.56258,"totalSupply":11287544271.56258,"rank":2449,"type":"crypto"},{"id":52,"symbol":"STRAT","name":"Stratis","circulatingSupply":100074480.17004512,"totalSupply":100074480.17004512,"rank":189,"type":"crypto"},{"id":487,"symbol":"STX","name":"Stox","circulatingSupply":49007665.50850411,"totalSupply":54753279.33279679,"rank":515,"type":"crypto"},{"id":120,"symbol":"SUB","name":"Substratum","circulatingSupply":471964025.67999995,"totalSupply":592000000,"rank":457,"type":"crypto"},{"id":821,"symbol":"SUMO","name":"Sumokoin","circulatingSupply":8166589,"totalSupply":17055478,"rank":767,"type":"crypto"},{"id":105,"symbol":"SYS","name":"Syscoin","circulatingSupply":null,"totalSupply":null,"rank":435,"type":"crypto"},{"id":506,"symbol":"TAAS","name":"TaaS","circulatingSupply":8145560.0265,"totalSupply":8146000.779398,"rank":1811,"type":"crypto"},{"id":424,"symbol":"TAU","name":"Lamden","circulatingSupply":288090566.88598657,"totalSupply":288090567.4938866,"rank":512,"type":"crypto"},{"id":857,"symbol":"TBX","name":"Tokenbox","circulatingSupply":11393882,"totalSupply":16051590,"rank":769,"type":"crypto"},{"id":133,"symbol":"TEL","name":"Telcoin","circulatingSupply":34752063230,"totalSupply":100000000000,"rank":204,"type":"crypto"},{"id":149,"symbol":"TEN","name":"Tokenomy","circulatingSupply":200000000,"totalSupply":200000000,"rank":523,"type":"crypto"},{"id":357,"symbol":"TERN","name":"Ternio","circulatingSupply":409274561,"totalSupply":999924300,"rank":567,"type":"crypto"},{"id":96,"symbol":"THETA","name":"Theta Network","circulatingSupply":999999900,"totalSupply":1000000000,"rank":24,"type":"crypto"},{"id":372,"symbol":"TIX","name":"Blocktix","circulatingSupply":40000000,"totalSupply":62500000,"rank":760,"type":"crypto"},{"id":365,"symbol":"TKN","name":"TokenCard","circulatingSupply":23987561.9283204,"totalSupply":39406759.9283204,"rank":497,"type":"crypto"},{"id":693,"symbol":"TKS","name":"Tokes Platform","circulatingSupply":999999999.8666543,"totalSupply":999999999.8666543,"rank":3130,"type":"crypto"},{"id":186,"symbol":"TNB","name":"Time New Bank","circulatingSupply":2459435804,"totalSupply":4515707418,"rank":297,"type":"crypto"},{"id":549,"symbol":"TNC","name":"Trinity Network Credit","circulatingSupply":333333333,"totalSupply":1000000000,"rank":800,"type":"crypto"},{"id":292,"symbol":"TNT","name":"Tierion","circulatingSupply":428481269,"totalSupply":1000000000,"rank":617,"type":"crypto"},{"id":159,"symbol":"TOMO","name":"TomoChain","circulatingSupply":55000000,"totalSupply":100000000,"rank":146,"type":"crypto"},{"id":197,"symbol":"TPAY","name":"TokenPay","circulatingSupply":15657277,"totalSupply":19624870,"rank":369,"type":"crypto"},{"id":511,"symbol":"TRIG","name":"Triggers","circulatingSupply":32105578,"totalSupply":100000000,"rank":1796,"type":"crypto"},{"id":4393,"symbol":"TRTL","name":"TurtleCoin","circulatingSupply":35103557909,"totalSupply":1000000000000,"rank":390,"type":"crypto"},{"id":11,"symbol":"TRX","name":"TRON","circulatingSupply":66140232427,"totalSupply":99281283754,"rank":25,"type":"crypto"},{"id":274,"symbol":"TUSD","name":"TrueUSD","circulatingSupply":415216039.37,"totalSupply":415216039.37,"rank":68,"type":"crypto"},{"id":966,"symbol":"TZC","name":"TrezarCoin","circulatingSupply":95718600,"totalSupply":107718600,"rank":820,"type":"crypto"},{"id":183,"symbol":"UBQ","name":"Ubiq","circulatingSupply":null,"totalSupply":null,"rank":2405,"type":"crypto"},{"id":69380,"symbol":"UMA","name":"UMA","circulatingSupply":55632664.61517005,"totalSupply":101257295.50113645,"rank":58,"type":"crypto"},{"id":1001,"symbol":"UNI","name":"Uniswap","circulatingSupply":44117235,"totalSupply":112000000,"rank":73,"type":"crypto"},{"id":1989,"symbol":"UNITY","name":"SuperNET","circulatingSupply":null,"totalSupply":null,"rank":7948,"type":"crypto"},{"id":1509,"symbol":"USD","name":"US Dollar","circulatingSupply":11976502.87,"totalSupply":11976502.87,"rank":null,"type":"fiat"},{"id":1760,"symbol":"USDC","name":"USD Coin","circulatingSupply":5074573630.598724,"totalSupply":5074579631.846146,"rank":13,"type":"crypto"},{"id":8,"symbol":"USDT","name":"Tether","circulatingSupply":24358133817.42862,"totalSupply":24520493732.78001,"rank":3,"type":"crypto"},{"id":231,"symbol":"UTK","name":"UTRUST","circulatingSupply":450000000,"totalSupply":500000000,"rank":128,"type":"crypto"},{"id":138,"symbol":"VERI","name":"Veritaseum","circulatingSupply":99999993.292,"totalSupply":100000000,"rank":2917,"type":"crypto"},{"id":19,"symbol":"VET","name":"VeChain","circulatingSupply":64850448123,"totalSupply":85985041177,"rank":29,"type":"crypto"},{"id":259,"symbol":"VIA","name":"Viacoin","circulatingSupply":null,"totalSupply":null,"rank":426,"type":"crypto"},{"id":391,"symbol":"VIB","name":"Viberate","circulatingSupply":177631464,"totalSupply":200000000,"rank":327,"type":"crypto"},{"id":252,"symbol":"VIBE","name":"VIBE","circulatingSupply":260080096,"totalSupply":267000000,"rank":302,"type":"crypto"},{"id":1108,"symbol":"VIVO","name":"VIVO","circulatingSupply":3059811,"totalSupply":3879811,"rank":2826,"type":"crypto"},{"id":561,"symbol":"VRC","name":"VeriCoin","circulatingSupply":null,"totalSupply":null,"rank":416,"type":"crypto"},{"id":10750,"symbol":"VRSC","name":"VerusCoin","circulatingSupply":null,"totalSupply":null,"rank":10176,"type":"crypto"},{"id":142,"symbol":"VTC","name":"Vertcoin","circulatingSupply":46879925,"totalSupply":84000000,"rank":273,"type":"crypto"},{"id":4235,"symbol":"VTHO","name":"VeThor Token","circulatingSupply":null,"totalSupply":null,"rank":6854,"type":"crypto"},{"id":313,"symbol":"WABI","name":"Tael","circulatingSupply":52478516,"totalSupply":100000000,"rank":306,"type":"crypto"},{"id":60,"symbol":"WAN","name":"Wanchain","circulatingSupply":106152493,"totalSupply":210000000,"rank":181,"type":"crypto"},{"id":43,"symbol":"WAVES","name":"Waves","circulatingSupply":104044703.5883976,"totalSupply":104083726,"rank":52,"type":"crypto"},{"id":97,"symbol":"WAX","name":"WAX","circulatingSupply":1849998504.51,"totalSupply":1850000000,"rank":455,"type":"crypto"},{"id":1984,"symbol":"WBTC","name":"Wrapped Bitcoin","circulatingSupply":null,"totalSupply":null,"rank":2358,"type":"crypto"},{"id":131,"symbol":"WGR","name":"Wagerr","circulatingSupply":198359305.46787024,"totalSupply":198359305.46787024,"rank":504,"type":"crypto"},{"id":4180,"symbol":"WICC","name":"WaykiChain","circulatingSupply":1886626.6857380867,"totalSupply":210000000,"rank":387,"type":"crypto"},{"id":273,"symbol":"WINGS","name":"Wings","circulatingSupply":96893094,"totalSupply":100000000,"rank":562,"type":"crypto"},{"id":267,"symbol":"WPR","name":"WePower","circulatingSupply":509811562.0967742,"totalSupply":745248183.0967742,"rank":303,"type":"crypto"},{"id":87,"symbol":"WTC","name":"Waltonchain","circulatingSupply":26535115.165858533,"totalSupply":70000000,"rank":271,"type":"crypto"},{"id":null,"symbol":"X","name":"GLX Equity Token","circulatingSupply":null,"totalSupply":null,"rank":2000,"type":"crypto"},{"id":232,"symbol":"XAS","name":"Asch","circulatingSupply":93355331,"totalSupply":100000000,"rank":364,"type":"crypto"},{"id":952,"symbol":"XBC","name":"Bitcoin Plus","circulatingSupply":null,"totalSupply":null,"rank":1152,"type":"crypto"},{"id":1027,"symbol":"XBP","name":"BlitzPredict","circulatingSupply":null,"totalSupply":null,"rank":10577,"type":"crypto"},{"id":261,"symbol":"XBY","name":"XtraBYtes","circulatingSupply":430000000,"totalSupply":649999999.9989929,"rank":612,"type":"crypto"},{"id":385,"symbol":"XCP","name":"Counterparty","circulatingSupply":null,"totalSupply":null,"rank":2101,"type":"crypto"},{"id":194,"symbol":"XDN","name":"DigitalNote","circulatingSupply":6928822446,"totalSupply":7130019340,"rank":507,"type":"crypto"},{"id":17,"symbol":"XEM","name":"NEM","circulatingSupply":7076804301.046602,"totalSupply":8999999999,"rank":32,"type":"crypto"},{"id":4457,"symbol":"XIN","name":"Infinity Economics","circulatingSupply":null,"totalSupply":null,"rank":6709,"type":"crypto"},{"id":6,"symbol":"XLM","name":"Stellar","circulatingSupply":20205523566.63592,"totalSupply":49999999738.63592,"rank":11,"type":"crypto"},{"id":1003,"symbol":"XMCC","name":"Monoeci","circulatingSupply":8069493,"totalSupply":9507271,"rank":2901,"type":"crypto"},{"id":948,"symbol":"XMG","name":"Magi","circulatingSupply":null,"totalSupply":null,"rank":1168,"type":"crypto"},{"id":1770,"symbol":"XMO","name":"Monero Original","circulatingSupply":null,"totalSupply":null,"rank":8076,"type":"crypto"},{"id":10,"symbol":"XMR","name":"Monero","circulatingSupply":17816131.495106976,"totalSupply":17816131.495106976,"rank":17,"type":"crypto"},{"id":463,"symbol":"XMY","name":"Myriad","circulatingSupply":1620160750,"totalSupply":2000000000,"rank":557,"type":"crypto"},{"id":523,"symbol":"XP","name":"XP","circulatingSupply":197248134066,"totalSupply":242787367044,"rank":463,"type":"crypto"},{"id":512,"symbol":"XPA","name":"XPA","circulatingSupply":48613632.24920708,"totalSupply":10000000000,"rank":1042,"type":"crypto"},{"id":248,"symbol":"XPM","name":"Primecoin","circulatingSupply":null,"totalSupply":null,"rank":2259,"type":"crypto"},{"id":3,"symbol":"XRP","name":"XRP","circulatingSupply":44073177235,"totalSupply":99990980257,"rank":5,"type":"crypto"},{"id":3,"symbol":"XRP","name":"XRP","circulatingSupply":44073177235,"totalSupply":99990980257,"rank":5,"type":"crypto"},{"id":919,"symbol":"XSG","name":"SnowGem","circulatingSupply":9316287,"totalSupply":84096000,"rank":770,"type":"crypto"},{"id":18,"symbol":"XTZ","name":"Tezos","circulatingSupply":757135004.964199,"totalSupply":863415973.138551,"rank":21,"type":"crypto"},{"id":1606,"symbol":"XUC","name":"Exchange Union","circulatingSupply":3000000000,"totalSupply":3000000000,"rank":2918,"type":"crypto"},{"id":3311,"symbol":"XVC","name":"Vcash","circulatingSupply":null,"totalSupply":null,"rank":2138,"type":"crypto"},{"id":40,"symbol":"XVG","name":"Verge","circulatingSupply":16420665543.363379,"totalSupply":16420665543.363379,"rank":96,"type":"crypto"},{"id":100,"symbol":"XZC","name":"Zcoin","circulatingSupply":10094568,"totalSupply":10094568,"rank":159,"type":"crypto"},{"id":71246,"symbol":"YFI","name":"yearn.finance","circulatingSupply":29968.790550817273,"totalSupply":30000,"rank":40,"type":"crypto"},{"id":349,"symbol":"YOYOW","name":"YOYOW","circulatingSupply":299999990,"totalSupply":300000000,"rank":571,"type":"crypto"},{"id":226,"symbol":"ZCL","name":"Zclassic","circulatingSupply":5292363,"totalSupply":21000000,"rank":654,"type":"crypto"},{"id":21,"symbol":"ZEC","name":"Zcash","circulatingSupply":10933012.5,"totalSupply":10933012.5,"rank":41,"type":"crypto"},{"id":4350,"symbol":"ZEL","name":"ZelCash","circulatingSupply":null,"totalSupply":null,"rank":6779,"type":"crypto"},{"id":86,"symbol":"ZEN","name":"Horizen","circulatingSupply":5165975,"totalSupply":21000000,"rank":106,"type":"crypto"},{"id":769,"symbol":"ZEST","name":"Zest","circulatingSupply":2272798,"totalSupply":2314063,"rank":1490,"type":"crypto"},{"id":769,"symbol":"ZEST","name":"Zest","circulatingSupply":2272798,"totalSupply":2314063,"rank":1490,"type":"crypto"},{"id":34,"symbol":"ZIL","name":"Zilliqa","circulatingSupply":12015669927.289948,"totalSupply":21000000000,"rank":51,"type":"crypto"},{"id":25,"symbol":"ZRX","name":"0x","circulatingSupply":750237553.4434261,"totalSupply":1000000000,"rank":65,"type":"crypto"}]